pyrofi/__init__.py
pyrofi/__main__.py
pyrofi-0.3.0.dist-info/WHEEL
pyrofi-0.3.0.dist-info/METADATA
pyrofi-0.3.0.dist-info/RECORD
