Metadata-Version: 2.1
Name: pyrofi
Version: 0.3.0
Summary: Rofi Menu wrapper for hierarchical menu creation.
Home-page: https://github.com/astynax/pyrofi
License: MIT
Author: Aleksei Pirogov
Author-email: astynax@users.noreply.github.com
Requires-Python: >=3.6,<4.0
Classifier: Development Status :: 4 - Beta
Classifier: License :: OSI Approved :: MIT License
Classifier: Operating System :: Unix
Classifier: Programming Language :: Python :: 3
Classifier: Programming Language :: Python :: 3 :: Only
Classifier: Programming Language :: Python :: 3.6
Classifier: Programming Language :: Python :: 3.7
Classifier: Programming Language :: Python :: 3.8
Classifier: Topic :: Software Development :: User Interfaces
Classifier: Typing :: Typed
Project-URL: Repository, https://github.com/astynax/pyrofi
